intelliprove/api/__init__.py
intelliprove/api/api_service.py
intelliprove/api/exceptions/__init__.py
intelliprove/api/exceptions/api.py
intelliprove/api/exceptions/media.py
intelliprove/api/exceptions/uuid.py
intelliprove/api/intelliprove_api.py
intelliprove/api/models/__init__.py
intelliprove/api/models/dataclasses/__init__.py
intelliprove/api/models/dataclasses/biomarkers.py
intelliprove/api/models/dataclasses/quality.py
intelliprove/api/models/dataclasses/settings.py
intelliprove/api/models/enums.py
intelliprove/api/models/responses/__init__.py
intelliprove/api/models/responses/biomarkers_response.py
intelliprove/api/models/responses/quality_response.py
intelliprove/api/models/responses/unprocessable_video_response.py
intelliprove/api/utils/__init__.py
intelliprove/api/utils/identifiers.py
intelliprove/api/utils/media.py
intelliprove-1.2.0.dist-info/METADATA
intelliprove-1.2.0.dist-info/WHEEL
intelliprove-1.2.0.dist-info/RECORD
