Metadata-Version: 2.1
Name: intelliprove
Version: 1.2.0
Summary: The Python SDK for using IntelliProve.
Author: Seppe De Langhe
Author-email: seppe.delanghe@intelliprove.com
Requires-Python: >=3.9,<4.0
Classifier: Programming Language :: Python :: 3
Classifier: Programming Language :: Python :: 3.9
Classifier: Programming Language :: Python :: 3.10
Classifier: Programming Language :: Python :: 3.11
Classifier: Programming Language :: Python :: 3.12
Requires-Dist: opencv-python (>=4.7.0.68,<5.0.0.0)
Requires-Dist: requests (>=2.28.1,<3.0.0)
